visualisation_package/__init__.py
visualisation_package/data/__init__.py
visualisation_package/vis_tools/__init__.py
visualisation_package/vis_tools/baseline.py
visualisation_package/vis_tools/datasets.py
visualisation_package/vis_tools/deprivation.py
visualisation_package/vis_tools/visualisation.py
vistools_for_screening666-0.3.0.dist-info/LICENSE
vistools_for_screening666-0.3.0.dist-info/METADATA
vistools_for_screening666-0.3.0.dist-info/WHEEL
vistools_for_screening666-0.3.0.dist-info/top_level.txt
vistools_for_screening666-0.3.0.dist-info/RECORD
