Metadata-Version: 2.1
Name: vistools-for-screening666
Version: 0.3.0
Summary: A collection of tools to aid with visualisation of screening        uptake data
Home-page: https://github.com/mangotangochick/visualisation-tools-for-screening.git
Author: Ieva, Frances, Alistair
Author-email: ij229@exeter.ac.uk
License: The MIT License (MIT)
Platform: UNKNOWN
Classifier: Programming Language :: Python :: 3.6
Classifier: Programming Language :: Python :: 3.7
Classifier: Programming Language :: Python :: 3.8
Classifier: License :: OSI Approved :: MIT License
Classifier: Operating System :: OS Independent
Requires-Python: >=3.6.9
License-File: LICENSE
Requires-Dist: matplotlib (>=3.1.3)
Requires-Dist: numpy (>=1.18.1)
Requires-Dist: pandas (>=1.0.1)
Requires-Dist: scipy (>=1.4.1)
Requires-Dist: seaborn (>=0.10.0)
